cs101_testing/__init__.py
cs101_testing/testing_lab02.py
cs101_testing-0.0.3.dist-info/LICENSE
cs101_testing-0.0.3.dist-info/METADATA
cs101_testing-0.0.3.dist-info/WHEEL
cs101_testing-0.0.3.dist-info/top_level.txt
cs101_testing-0.0.3.dist-info/RECORD
